RTMPSender/RTMPSender.py
RTMPSender/__init__.py
RTPSender/RTPSender.py
RTPSender/__init__.py
RTPSender-3.9.4.2.dist-info/METADATA
RTPSender-3.9.4.2.dist-info/WHEEL
RTPSender-3.9.4.2.dist-info/top_level.txt
RTPSender-3.9.4.2.dist-info/RECORD
