Metadata-Version: 2.1
Name: RTPSender
Version: 3.9.4.2
Summary: A SDK for sending RTP and RTMP streams
Author: liushihai02
Author-email: liushihai02@58.com
Requires-Python: >=3.9
Requires-Dist: scapy
Requires-Dist: opencv-python
Requires-Dist: pydub
Requires-Dist: loguru
Requires-Dist: python-librtmp
